kno_sdk/__init__.py
kno_sdk/agent.py
kno_sdk/constant.py
kno_sdk/embedding.py
kno_sdk/git.py
kno_sdk-1.4.10.dist-info/METADATA
kno_sdk-1.4.10.dist-info/WHEEL
kno_sdk-1.4.10.dist-info/RECORD
