Metadata-Version: 2.4
Name: kno-sdk
Version: 1.4.10
Summary: Clone GitHub repos, build embeddings, store in Chroma, and search.
Author-email: Your Name <you@example.com>
License: MIT
Requires-Dist: gitpython==3.1.44
Requires-Dist: langchain-anthropic==0.3.12
Requires-Dist: langchain-chroma==0.2.3
Requires-Dist: langchain-openai==0.3.14
Requires-Dist: langchain==0.3.24
Requires-Dist: langgraph==0.3.33
Requires-Dist: sentence-transformers==4.1.0
Requires-Dist: transformers==4.51.3
Requires-Dist: tree-sitter-languages==1.10.2
Requires-Dist: tree-sitter==0.20.2
